icukit/__init__.py
icukit/alpha_index.py
icukit/bidi.py
icukit/breaker.py
icukit/calendar.py
icukit/collator.py
icukit/compact.py
icukit/datetime.py
icukit/discover.py
icukit/displayname.py
icukit/duration.py
icukit/errors.py
icukit/formatters.py
icukit/idna.py
icukit/list_format.py
icukit/locale.py
icukit/measure.py
icukit/message.py
icukit/parse.py
icukit/plural.py
icukit/regex.py
icukit/region.py
icukit/script.py
icukit/search.py
icukit/spoof.py
icukit/timezone.py
icukit/transliterator.py
icukit/unicode.py
icukit/cli/__init__.py
icukit/cli/__main__.py
icukit/cli/base.py
icukit/cli/command_trie.py
icukit/cli/locale_helpers.py
icukit/cli/logging_setup.py
icukit/cli/main.py
icukit/cli/output_helpers.py
icukit/cli/subcommand_base.py
icukit/cli/command/__init__.py
icukit/cli/command/alpha_index.py
icukit/cli/command/bidi.py
icukit/cli/command/breaker.py
icukit/cli/command/calendar.py
icukit/cli/command/collator.py
icukit/cli/command/compact.py
icukit/cli/command/datetime.py
icukit/cli/command/discover.py
icukit/cli/command/displayname.py
icukit/cli/command/duration.py
icukit/cli/command/help_cmd.py
icukit/cli/command/idna.py
icukit/cli/command/listfmt.py
icukit/cli/command/locale.py
icukit/cli/command/measure.py
icukit/cli/command/message.py
icukit/cli/command/parse.py
icukit/cli/command/plural.py
icukit/cli/command/regex.py
icukit/cli/command/region.py
icukit/cli/command/script.py
icukit/cli/command/search.py
icukit/cli/command/sort.py
icukit/cli/command/spoof.py
icukit/cli/command/timezone.py
icukit/cli/command/transliterate.py
icukit/cli/command/unicode.py
icukit-0.1.2.dist-info/licenses/LICENSE
icukit-0.1.2.dist-info/METADATA
icukit-0.1.2.dist-info/WHEEL
icukit-0.1.2.dist-info/entry_points.txt
icukit-0.1.2.dist-info/top_level.txt
icukit-0.1.2.dist-info/RECORD
