Metadata-Version: 2.4
Name: icukit
Version: 0.1.2
Summary: ICU toolkit - library and CLI for Unicode and internationalization
Author-email: Kevin Lenzo <kevinlenzo@gmail.com>
License: MIT
Project-URL: Homepage, https://github.com/lenzo-ka/icukit
Project-URL: Repository, https://github.com/lenzo-ka/icukit
Project-URL: Issues, https://github.com/lenzo-ka/icukit/issues
Keywords: icu,unicode,i18n,internationalization,localization,text,collation,formatting
Classifier: Development Status :: 4 - Beta
Classifier: Intended Audience :: Developers
Classifier: License :: OSI Approved :: MIT License
Classifier: Operating System :: MacOS
Classifier: Operating System :: POSIX :: Linux
Classifier: Programming Language :: Python :: 3
Classifier: Programming Language :: Python :: 3.9
Classifier: Programming Language :: Python :: 3.10
Classifier: Programming Language :: Python :: 3.11
Classifier: Programming Language :: Python :: 3.12
Classifier: Programming Language :: Python :: 3.13
Classifier: Programming Language :: Python :: 3.14
Classifier: Topic :: Software Development :: Internationalization
Classifier: Topic :: Software Development :: Localization
Classifier: Topic :: Text Processing
Requires-Python: >=3.9
License-File: LICENSE
Requires-Dist: icukit-pyicu>=78.2.1
Provides-Extra: dev
Requires-Dist: pytest>=9.0; extra == "dev"
Dynamic: license-file
